chassis2024/__init__.py
chassis2024/chassis.py
chassis2024/exceptions.py
chassis2024/kahn.py
chassis2024/words.py
chassis2024/argparse/__init__.py
chassis2024/argparse/words.py
chassis2024/basicjsonpersistence/__init__.py
chassis2024/basicjsonpersistence/words.py
chassis2024/basicrun/__init__.py
chassis2024-1.0.0.dist-info/LICENSE
chassis2024-1.0.0.dist-info/METADATA
chassis2024-1.0.0.dist-info/WHEEL
chassis2024-1.0.0.dist-info/top_level.txt
chassis2024-1.0.0.dist-info/RECORD
