Metadata-Version: 2.1
Name: chassis2024
Version: 1.0.0
Summary: a flexible chassis for assembling Python programs from parts
Home-page: https://github.com/LionKimbro/chassis2024
Author: Lion Kimbro
Author-email: Lion Kimbro <lionkimbro@gmail.com>
Project-URL: Homepage, https://github.com/lionkimbro/chassis2024
Project-URL: Bug Tracker, https://github.com/lionkimbro/chassis2024/issues
Keywords: chassis,framework,infrastructure
Classifier: Programming Language :: Python :: 3
Classifier: License :: OSI Approved :: BSD License
Classifier: Operating System :: OS Independent
Requires-Python: >=3.7
License-File: LICENSE
